{"result_ingredients": [{"class": "salt", "prob": "0.984178"}, {"class": "butter", "prob": "0.916485"}, {"class": "pepper", "prob": "0.966306"}, {"class": "unsalted_butter", "prob": "0.802807"}, {"class": "green_onions", "prob": "0.50967"}, {"class": "heavy_cream", "prob": "0.982952"}, {"class": "bacon", "prob": "0.953509"}, {"class": "chicken_broth", "prob": "0.910011"}, {"class": "grits", "prob": "0.996494"}, {"class": "grit_quick", "prob": "0.7147"}], "result_recognition": [{"class": "shrimp_and_grits", "prob": "0.998267"}, {"class": "omelette", "prob": "0.000730429"}, {"class": "sauteed_spinach_with_prawns", "prob": "0.00033945"}, {"class": "garlic_soup", "prob": "0.000200085"}, {"class": "lobster_bisque", "prob": "9.97197e-05"}], "img_url": "https://s3-media1.fl.yelpcdn.com/bphoto/Yodb6IwOGZOcqzoaHx5xUw/o.jpg", "img_path": "/media/HDD_2TB/LogMeal/api_dev//images/img_downloaded.jpg", "result_family": [{"class": "seafood", "prob": "0.833089"}, {"class": "soup", "prob": "0.132242"}, {"class": "vegetable_fruit", "prob": "0.0303607"}, {"class": "meat", "prob": "0.00189233"}, {"class": "bread", "prob": "0.00173832"}, {"class": "egg", "prob": "0.000254364"}, {"class": "dessert", "prob": "0.000196253"}, {"class": "noodles_pasta", "prob": "0.000161965"}, {"class": "rice", "prob": "4.62105e-05"}, {"class": "fried_food", "prob": "1.64881e-05"}, {"class": "dairy_products", "prob": "2.32263e-06"}]}