{"result_ingredients": [{"class": "salt", "prob": "0.760857"}, {"class": "butter", "prob": "0.99016"}, {"class": "unsalted_butter", "prob": "0.906226"}, {"class": "english_muffins", "prob": "0.790495"}], "result_recognition": [{"class": "escudella_amb_carn_d'olla", "prob": "0.306859"}, {"class": "eggs_benedict", "prob": "0.262606"}, {"class": "toasts_with_smoked_salmon", "prob": "0.208309"}, {"class": "vegetable_and_millet_soup", "prob": "0.0545353"}, {"class": "bread_with_hazelnut_cocoa_spread", "prob": "0.026651"}], "img_url": "https://s3-media2.fl.yelpcdn.com/bphoto/byPHKSg1mtEzHkg0W5_qIg/o.jpg", "img_path": "/media/HDD_2TB/LogMeal/api_dev//images/img_downloaded.jpg", "result_family": [{"class": "dessert", "prob": "0.512136"}, {"class": "egg", "prob": "0.197778"}, {"class": "soup", "prob": "0.142052"}, {"class": "meat", "prob": "0.099919"}, {"class": "rice", "prob": "0.0179883"}, {"class": "seafood", "prob": "0.0148512"}, {"class": "bread", "prob": "0.0116604"}, {"class": "fried_food", "prob": "0.00280664"}, {"class": "vegetable_fruit", "prob": "0.000764141"}, {"class": "dairy_products", "prob": "3.0775e-05"}, {"class": "noodles_pasta", "prob": "1.37327e-05"}]}