{"result_ingredients": [{"class": "salt", "prob": "0.89516"}, {"class": "cheddar_cheese", "prob": "0.641167"}], "result_recognition": [{"class": "cuban-style_rice", "prob": "0.347484"}, {"class": "cous_cous_with_vegetables_and_meat", "prob": "0.274636"}, {"class": "omelette", "prob": "0.100957"}, {"class": "grilled_turkey", "prob": "0.0995017"}, {"class": "toasts_with_jam", "prob": "0.0527506"}], "img_url": "https://s3-media2.fl.yelpcdn.com/bphoto/Jr-1-eBL7cIijcI7New0mA/o.jpg", "img_path": "/media/HDD_2TB/LogMeal/api_dev//images/img_downloaded.jpg", "result_family": [{"class": "meat", "prob": "0.882129"}, {"class": "seafood", "prob": "0.0421412"}, {"class": "egg", "prob": "0.0262782"}, {"class": "bread", "prob": "0.0209557"}, {"class": "noodles_pasta", "prob": "0.0101355"}, {"class": "soup", "prob": "0.00907"}, {"class": "vegetable_fruit", "prob": "0.00841444"}, {"class": "rice", "prob": "0.000709939"}, {"class": "dessert", "prob": "7.3893e-05"}, {"class": "dairy_products", "prob": "5.19218e-05"}, {"class": "fried_food", "prob": "3.99394e-05"}]}