{"result_ingredients": [{"class": "salt", "prob": "0.800284"}, {"class": "green_onions", "prob": "0.51433"}, {"class": "heavy_cream", "prob": "0.907647"}, {"class": "cheddar_cheese", "prob": "0.89962"}, {"class": "cajun_seasoning", "prob": "0.602828"}], "result_recognition": [{"class": "shrimp_and_grits", "prob": "0.999896"}, {"class": "riojan-style_potatoes", "prob": "5.23067e-05"}, {"class": "sauteed_spinach_with_prawns", "prob": "1.13393e-05"}, {"class": "hot_and_sour_soup", "prob": "7.47405e-06"}, {"class": "hot_dog", "prob": "6.88955e-06"}], "img_url": "https://s3-media4.fl.yelpcdn.com/bphoto/jVD125gnelX3NPKsfo97Dw/o.jpg", "img_path": "/media/HDD_2TB/LogMeal/api_dev//images/img_downloaded.jpg", "result_family": [{"class": "seafood", "prob": "0.931646"}, {"class": "soup", "prob": "0.0463861"}, {"class": "vegetable_fruit", "prob": "0.0152797"}, {"class": "egg", "prob": "0.00227041"}, {"class": "dessert", "prob": "0.00197805"}, {"class": "meat", "prob": "0.00123153"}, {"class": "bread", "prob": "0.000925618"}, {"class": "noodles_pasta", "prob": "0.000165585"}, {"class": "fried_food", "prob": "5.6871e-05"}, {"class": "rice", "prob": "4.88999e-05"}, {"class": "dairy_products", "prob": "1.16873e-05"}]}