{"result_ingredients": [], "result_recognition": [{"class": "omelette", "prob": "0.977629"}, {"class": "hummus", "prob": "0.00338005"}, {"class": "cottage_cheese_with_honey", "prob": "0.00191742"}, {"class": "pea_soup", "prob": "0.00127616"}, {"class": "prime_rib", "prob": "0.00124302"}], "img_url": "https://s3-media4.fl.yelpcdn.com/bphoto/OPoHMPj5xSCC0erCk1Hofw/o.jpg", "img_path": "/media/HDD_2TB/LogMeal/api_dev//images/img_downloaded.jpg", "result_family": [{"class": "bread", "prob": "0.721245"}, {"class": "egg", "prob": "0.118291"}, {"class": "dessert", "prob": "0.0736488"}, {"class": "soup", "prob": "0.0271511"}, {"class": "vegetable_fruit", "prob": "0.0239542"}, {"class": "noodles_pasta", "prob": "0.0211829"}, {"class": "seafood", "prob": "0.0101924"}, {"class": "meat", "prob": "0.00237288"}, {"class": "rice", "prob": "0.000972712"}, {"class": "fried_food", "prob": "0.000695185"}, {"class": "dairy_products", "prob": "0.000294258"}]}