{"result_ingredients": [{"class": "salt", "prob": "0.563164"}, {"class": "butter", "prob": "0.774875"}], "result_recognition": [{"class": "fermented_cabbage", "prob": "0.294436"}, {"class": "lobster_bisque", "prob": "0.118214"}, {"class": "garlic_soup", "prob": "0.0899492"}, {"class": "macaroni_and_cheese", "prob": "0.0713326"}, {"class": "cottage_cheese_with_honey", "prob": "0.0630286"}], "img_url": "https://s3-media3.fl.yelpcdn.com/bphoto/urKBLw0XEBRyBiQeJ9-1HQ/o.jpg", "img_path": "/media/HDD_2TB/LogMeal/api_dev//images/img_downloaded.jpg", "result_family": [{"class": "soup", "prob": "0.985414"}, {"class": "noodles_pasta", "prob": "0.0103219"}, {"class": "vegetable_fruit", "prob": "0.0029813"}, {"class": "bread", "prob": "0.000644221"}, {"class": "meat", "prob": "0.00021741"}, {"class": "dessert", "prob": "0.000165937"}, {"class": "egg", "prob": "0.000138491"}, {"class": "seafood", "prob": "6.38919e-05"}, {"class": "rice", "prob": "2.53914e-05"}, {"class": "fried_food", "prob": "1.64867e-05"}, {"class": "dairy_products", "prob": "1.09075e-05"}]}