{"result_ingredients": [{"class": "eggs", "prob": "0.845606"}, {"class": "all-purpose_flour", "prob": "0.710582"}, {"class": "kosher_salt", "prob": "0.642782"}, {"class": "white_vinegar", "prob": "0.541749"}, {"class": "white_sugar", "prob": "0.799004"}, {"class": "beef", "prob": "0.876335"}], "result_recognition": [{"class": "strawberries_and_cream", "prob": "0.191401"}, {"class": "jam\u00f3n_serrano", "prob": "0.18009"}, {"class": "dark_chocolate", "prob": "0.170821"}, {"class": "bread_with_hazelnut_cocoa_spread", "prob": "0.0564077"}, {"class": "longaniza", "prob": "0.0354111"}], "img_url": "https://s3-media3.fl.yelpcdn.com/bphoto/ggb25lt4J6GJ_S374cOAjg/o.jpg", "img_path": "/media/HDD_2TB/LogMeal/api_dev//images/img_downloaded.jpg", "result_family": [{"class": "meat", "prob": "0.677444"}, {"class": "vegetable_fruit", "prob": "0.134163"}, {"class": "dessert", "prob": "0.114838"}, {"class": "bread", "prob": "0.0450002"}, {"class": "soup", "prob": "0.0158754"}, {"class": "noodles_pasta", "prob": "0.00698882"}, {"class": "seafood", "prob": "0.00341309"}, {"class": "dairy_products", "prob": "0.00190367"}, {"class": "egg", "prob": "0.000239504"}, {"class": "rice", "prob": "0.000102506"}, {"class": "fried_food", "prob": "3.15729e-05"}]}