{"result_ingredients": [{"class": "butter", "prob": "0.6700441"}, {"class": "garlic", "prob": "0.5287837"}, {"class": "white_wine", "prob": "0.7881533"}, {"class": "mussels", "prob": "0.9999822"}], "result_recognition": [{"class": "hake_with_green_sauce", "prob": "0.78107333"}, {"class": "grilled_shrimp", "prob": "0.13871723"}, {"class": "paella", "prob": "0.025384583"}, {"class": "sauteed_spinach_with_prawns", "prob": "0.020798728"}, {"class": "mussels", "prob": "0.014069836"}], "img_url": "https://s3-media1.fl.yelpcdn.com/bphoto/XQ9Zzdx1u6myuzv2b5wCIQ/o.jpg", "img_path": "/media/HDD_2TB/LogMeal/api_dev//images/img_downloaded.jpg", "result_family": [{"class": "seafood", "prob": "0.9712354"}, {"class": "rice", "prob": "0.027900737"}, {"class": "noodles_pasta", "prob": "0.00036437166"}, {"class": "vegetable_fruit", "prob": "0.0002986473"}, {"class": "soup", "prob": "0.00015112468"}, {"class": "fried_food", "prob": "2.8177412e-05"}, {"class": "meat", "prob": "1.645511e-05"}, {"class": "egg", "prob": "2.0780674e-06"}, {"class": "bread", "prob": "1.7830237e-06"}, {"class": "dairy_products", "prob": "8.777267e-07"}, {"class": "dessert", "prob": "3.3896322e-07"}]}