{"result_ingredients": [{"class": "salt", "prob": "0.9356638"}, {"class": "butter", "prob": "0.6105128"}, {"class": "pepper", "prob": "0.8080557"}], "result_recognition": [{"class": "omelette", "prob": "0.911939"}, {"class": "french_toast", "prob": "0.06216266"}, {"class": "baked_chicken_with_vegetables", "prob": "0.009194666"}, {"class": "grilled_turkey", "prob": "0.0036688088"}, {"class": "pork_chop", "prob": "0.002341324"}], "img_url": "https://s3-media1.fl.yelpcdn.com/bphoto/oV1dgqSPVb0kf2T1ac0-_Q/o.jpg", "img_path": "/media/HDD_2TB/LogMeal/api_rel//images/img_downloaded.jpg", "result_family": [{"class": "egg", "prob": "0.99859565"}, {"class": "bread", "prob": "0.0011590956"}, {"class": "seafood", "prob": "0.00022698849"}, {"class": "meat", "prob": "9.566885e-06"}, {"class": "dessert", "prob": "6.4070823e-06"}, {"class": "fried_food", "prob": "1.0630094e-06"}, {"class": "rice", "prob": "5.226119e-07"}, {"class": "soup", "prob": "4.1610227e-07"}, {"class": "vegetable_fruit", "prob": "2.5389096e-07"}, {"class": "noodles_pasta", "prob": "2.5300908e-08"}, {"class": "dairy_products", "prob": "1.4347282e-08"}]}