{"result_foodtypes": [{"output": {"labels": ["non_food", "food", "ingredients", "drinks"], "probs": [4.925435860059224e-06, 0.9780096411705017, 0.021205365657806396, 0.0007800484891049564]}}], "img_path": "/media/HDD_2TB/LogMeal/api_rel//images/img_downloaded.jpg", "result_recognition": [{"class": "longaniza", "prob": "0.25314313"}, {"class": "blood_sausage", "prob": "0.17635122"}, {"class": "chorizo", "prob": "0.0945786"}, {"class": "lentils_with_chorizo", "prob": "0.039905943"}, {"class": "escudella_amb_carn_d'olla", "prob": "0.02898494"}], "result_ingredients": [{"class": "extra-virgin_olive_oil", "prob": "0.62631005"}, {"class": "oil", "prob": "0.57008094"}], "img_url": "https://s3-media2.fl.yelpcdn.com/bphoto/1gCFBiA91mxIYyutFzZAEw/o.jpg", "result_family": [{"class": "meat", "prob": "0.9781734"}, {"class": "rice", "prob": "0.006842633"}, {"class": "soup", "prob": "0.006678503"}, {"class": "dessert", "prob": "0.0032900532"}, {"class": "bread", "prob": "0.0025272188"}, {"class": "noodles_pasta", "prob": "0.0010437352"}, {"class": "seafood", "prob": "0.00086344115"}, {"class": "vegetable_fruit", "prob": "0.000356089"}, {"class": "dairy_products", "prob": "0.00016845319"}, {"class": "fried_food", "prob": "4.2008563e-05"}, {"class": "egg", "prob": "1.4468318e-05"}]}