{"result_ingredients": [{"class": "butter", "prob": "0.5901666"}, {"class": "water", "prob": "0.8077197"}, {"class": "sauce", "prob": "0.57158095"}, {"class": "mushrooms", "prob": "0.50176704"}, {"class": "stock", "prob": "0.537136"}], "result_recognition": [{"class": "mussels", "prob": "0.83190525"}, {"class": "grilled_asparagus", "prob": "0.08667576"}, {"class": "oysters", "prob": "0.033950955"}, {"class": "asparagus_with_ham", "prob": "0.014974293"}, {"class": "hake_with_green_sauce", "prob": "0.0038562275"}], "img_url": "https://s3-media3.fl.yelpcdn.com/bphoto/iP_sEbsKCcQrx8Wg_HRl9g/o.jpg", "img_path": "/media/HDD_2TB/LogMeal/api_rel//images/img_downloaded.jpg", "result_family": [{"class": "meat", "prob": "0.29572055"}, {"class": "soup", "prob": "0.22303379"}, {"class": "fried_food", "prob": "0.16560535"}, {"class": "egg", "prob": "0.11645116"}, {"class": "seafood", "prob": "0.07300133"}, {"class": "noodles_pasta", "prob": "0.06459313"}, {"class": "vegetable_fruit", "prob": "0.05650541"}, {"class": "rice", "prob": "0.0023515995"}, {"class": "bread", "prob": "0.0021073162"}, {"class": "dairy_products", "prob": "0.00059029146"}, {"class": "dessert", "prob": "4.009639e-05"}]}