{"result_ingredients": [{"class": "unsalted_butter", "prob": "0.7161321"}], "result_recognition": [{"class": "crab_cakes", "prob": "0.48297197"}, {"class": "falafel", "prob": "0.33798134"}, {"class": "wheat_gluten_with_vegetables", "prob": "0.048298232"}, {"class": "steak", "prob": "0.03887521"}, {"class": "brown_rice", "prob": "0.014482389"}], "img_url": "https://s3-media4.fl.yelpcdn.com/bphoto/BfoOqPLG81Sli-tyg7DCpg/o.jpg", "img_path": "/media/HDD_2TB/LogMeal/api_rel//images/img_downloaded.jpg", "result_family": [{"class": "seafood", "prob": "0.98048353"}, {"class": "vegetable_fruit", "prob": "0.016393948"}, {"class": "meat", "prob": "0.0022777007"}, {"class": "noodles_pasta", "prob": "0.0006856412"}, {"class": "soup", "prob": "0.00011051524"}, {"class": "bread", "prob": "2.9360215e-05"}, {"class": "rice", "prob": "1.2994095e-05"}, {"class": "egg", "prob": "2.3466978e-06"}, {"class": "fried_food", "prob": "2.1819064e-06"}, {"class": "dairy_products", "prob": "1.1710378e-06"}, {"class": "dessert", "prob": "6.0275255e-07"}]}