{"result_ingredients": [{"class": "sugar", "prob": "0.629051"}], "result_recognition": [{"class": "omelette", "prob": "0.8559154"}, {"class": "toasts_with_jam", "prob": "0.06306344"}, {"class": "fruit_crepe", "prob": "0.047914498"}, {"class": "chocolate_crepe", "prob": "0.013947332"}, {"class": "fish_with_lemon", "prob": "0.003904811"}], "img_url": "https://s3-media4.fl.yelpcdn.com/bphoto/iu3gSLYnxv1Hzc76yAvLWw/o.jpg", "img_path": "/media/HDD_2TB/LogMeal/api_rel//images/img_downloaded.jpg", "result_family": [{"class": "dessert", "prob": "0.56631315"}, {"class": "bread", "prob": "0.27865154"}, {"class": "meat", "prob": "0.09717716"}, {"class": "vegetable_fruit", "prob": "0.03379687"}, {"class": "soup", "prob": "0.016058745"}, {"class": "egg", "prob": "0.0054329876"}, {"class": "rice", "prob": "0.0011768073"}, {"class": "seafood", "prob": "0.0009096399"}, {"class": "dairy_products", "prob": "0.0003025357"}, {"class": "fried_food", "prob": "9.041444e-05"}, {"class": "noodles_pasta", "prob": "9.018271e-05"}]}