{"result_ingredients": [{"class": "garlic", "prob": "0.9727844"}, {"class": "vegetable_oil", "prob": "0.9904178"}, {"class": "mayonnaise", "prob": "0.5335144"}, {"class": "paprika", "prob": "0.5123568"}, {"class": "red_bell_pepper", "prob": "0.84832084"}, {"class": "chicken_broth", "prob": "0.8579512"}, {"class": "sauce", "prob": "0.6951905"}, {"class": "rice_noodles", "prob": "0.85828435"}, {"class": "bay_leaf", "prob": "0.90118396"}, {"class": "saffron_threads", "prob": "0.65774626"}, {"class": "lemon_wedges", "prob": "0.9347238"}], "result_recognition": [{"class": "pad_thai", "prob": "0.45840144"}, {"class": "curry_noodles_with_mushrooms", "prob": "0.15320985"}, {"class": "grilled_shrimp", "prob": "0.1405446"}, {"class": "seafood", "prob": "0.0992237"}, {"class": "sauteed_spinach_with_prawns", "prob": "0.056835696"}], "img_url": "https://s3-media3.fl.yelpcdn.com/bphoto/ObTsT0LnPs0Uav4a0yY1pg/o.jpg", "img_path": "/media/HDD_2TB/LogMeal/api_rel//images/img_downloaded.jpg", "result_family": [{"class": "rice", "prob": "0.99328905"}, {"class": "bread", "prob": "0.003750845"}, {"class": "meat", "prob": "0.0014046836"}, {"class": "noodles_pasta", "prob": "0.0006914454"}, {"class": "seafood", "prob": "0.0006686843"}, {"class": "soup", "prob": "7.4794625e-05"}, {"class": "vegetable_fruit", "prob": "6.066841e-05"}, {"class": "fried_food", "prob": "3.353647e-05"}, {"class": "egg", "prob": "2.5813424e-05"}, {"class": "dessert", "prob": "3.5277955e-07"}, {"class": "dairy_products", "prob": "1.1587815e-07"}]}