{"result_ingredients": [{"class": "salt", "prob": "0.70964795"}, {"class": "olive_oil", "prob": "0.929234"}, {"class": "pepper", "prob": "0.9655282"}, {"class": "avocado", "prob": "0.72165215"}, {"class": "lemon", "prob": "0.90861064"}, {"class": "lime", "prob": "0.95657843"}, {"class": "cilantro", "prob": "0.80248314"}, {"class": "smoked_paprika", "prob": "0.77049273"}, {"class": "sauce", "prob": "0.84132814"}, {"class": "salmon_fillets", "prob": "0.9457793"}, {"class": "black_sesame_seeds", "prob": "0.5781464"}, {"class": "sushi_grade_tuna", "prob": "0.5890869"}], "result_recognition": [{"class": "fermented_cabbage", "prob": "0.20116656"}, {"class": "pho", "prob": "0.15531744"}, {"class": "chorizo", "prob": "0.09392893"}, {"class": "stuffed_eggplant", "prob": "0.08663257"}, {"class": "fried_rice", "prob": "0.053527284"}], "img_url": "https://s3-media2.fl.yelpcdn.com/bphoto/LfRMiI2ypWHLY0IucvodvQ/o.jpg", "img_path": "/media/HDD_2TB/LogMeal/api_rel//images/img_downloaded.jpg", "result_family": [{"class": "seafood", "prob": "0.68245023"}, {"class": "bread", "prob": "0.21817808"}, {"class": "noodles_pasta", "prob": "0.076914564"}, {"class": "rice", "prob": "0.015629375"}, {"class": "vegetable_fruit", "prob": "0.0018353618"}, {"class": "meat", "prob": "0.001484506"}, {"class": "soup", "prob": "0.0014641407"}, {"class": "fried_food", "prob": "0.0010832147"}, {"class": "egg", "prob": "0.0009336038"}, {"class": "dairy_products", "prob": "2.382479e-05"}, {"class": "dessert", "prob": "3.1052543e-06"}]}