{"result_foodtypes": [{"output": {"labels": ["non_food", "food", "ingredients", "drinks"], "probs": [1.687339499767404e-05, 0.9993025064468384, 0.0006714568007737398, 9.135385880654212e-06]}}], "img_path": "/media/HDD_2TB/LogMeal/api_rel//images/img_downloaded.jpg", "result_recognition": [{"class": "chocolate_crepe", "prob": "0.99442124"}, {"class": "chocolate_cake", "prob": "0.0039172545"}, {"class": "french_toast", "prob": "0.0005050901"}, {"class": "baklava", "prob": "0.0002887916"}, {"class": "samosa", "prob": "0.00020711527"}], "result_ingredients": [{"class": "sugar", "prob": "0.71148866"}, {"class": "water", "prob": "0.8173083"}, {"class": "vanilla_extract", "prob": "0.6949485"}, {"class": "heavy_cream", "prob": "0.96118706"}, {"class": "baking_soda", "prob": "0.79015607"}], "img_url": "https://s3-media4.fl.yelpcdn.com/bphoto/sokDkiMJP9bfhO7hPsVgog/o.jpg", "result_family": [{"class": "dessert", "prob": "0.92029995"}, {"class": "bread", "prob": "0.079692006"}, {"class": "seafood", "prob": "4.52771e-06"}, {"class": "dairy_products", "prob": "1.706168e-06"}, {"class": "soup", "prob": "1.0841848e-06"}, {"class": "fried_food", "prob": "5.770111e-07"}, {"class": "vegetable_fruit", "prob": "1.2841222e-07"}, {"class": "egg", "prob": "3.7230325e-08"}, {"class": "meat", "prob": "7.469664e-09"}, {"class": "rice", "prob": "6.1703764e-10"}, {"class": "noodles_pasta", "prob": "5.1387744e-10"}]}