{"result_ingredients": [{"class": "sauce", "prob": "0.838164"}, {"class": "baguette", "prob": "0.844918"}, {"class": "red_wine_vinegar", "prob": "0.804547"}], "result_recognition": [{"class": "foie_gras", "prob": "0.523689"}, {"class": "gnocchi", "prob": "0.326156"}, {"class": "scallops", "prob": "0.075396"}, {"class": "french_toast", "prob": "0.0276349"}, {"class": "toscana-style_macaroni", "prob": "0.0128987"}], "img_url": "https://s3-media2.fl.yelpcdn.com/bphoto/86Mf4QBJEOvAniBbjlgoDg/o.jpg", "img_path": "/media/HDD_2TB/LogMeal/api_dev//images/img_downloaded.jpg", "result_family": [{"class": "seafood", "prob": "0.662679"}, {"class": "noodles_pasta", "prob": "0.0887737"}, {"class": "soup", "prob": "0.0634514"}, {"class": "meat", "prob": "0.0521295"}, {"class": "egg", "prob": "0.0475189"}, {"class": "dessert", "prob": "0.0416358"}, {"class": "bread", "prob": "0.0202392"}, {"class": "dairy_products", "prob": "0.0131229"}, {"class": "fried_food", "prob": "0.00793741"}, {"class": "rice", "prob": "0.00207266"}, {"class": "vegetable_fruit", "prob": "0.000439693"}]}