{"result_ingredients": [{"class": "salt", "prob": "0.58582866"}, {"class": "plain_greek_yogurt", "prob": "0.6688945"}], "result_recognition": [{"class": "garlic_soup", "prob": "0.23508099"}, {"class": "sponge_cake", "prob": "0.16339219"}, {"class": "pineapple_with_ham", "prob": "0.11965058"}, {"class": "cuban-style_rice", "prob": "0.098911084"}, {"class": "jelly", "prob": "0.07937003"}], "img_url": "https://s3-media4.fl.yelpcdn.com/bphoto/a43kyS0fjO9xBQgaUl6Rgw/o.jpg", "img_path": "/media/HDD_2TB/LogMeal/api_dev//images/img_downloaded.jpg", "result_family": [{"class": "dessert", "prob": "0.72037554"}, {"class": "seafood", "prob": "0.2220347"}, {"class": "meat", "prob": "0.025941769"}, {"class": "bread", "prob": "0.011699848"}, {"class": "vegetable_fruit", "prob": "0.010466708"}, {"class": "rice", "prob": "0.0061791344"}, {"class": "dairy_products", "prob": "0.0013832838"}, {"class": "fried_food", "prob": "0.0013490022"}, {"class": "egg", "prob": "0.00029621823"}, {"class": "soup", "prob": "0.00026201442"}, {"class": "noodles_pasta", "prob": "1.1780168e-05"}]}