{"result_ingredients": [{"class": "sesame_oil", "prob": "0.65160507"}, {"class": "french_fries", "prob": "0.60135186"}], "result_recognition": [{"class": "filet_mignon", "prob": "0.4771902"}, {"class": "steak", "prob": "0.2180679"}, {"class": "shrimp_and_grits", "prob": "0.09585366"}, {"class": "toscana-style_macaroni", "prob": "0.05761128"}, {"class": "poutine", "prob": "0.027422192"}], "img_url": "https://s3-media2.fl.yelpcdn.com/bphoto/Gvuc7lOdWlodeDYBDvsEKA/o.jpg", "img_path": "/media/HDD_2TB/LogMeal/api_rel//images/img_downloaded.jpg", "result_family": [{"class": "meat", "prob": "0.44259766"}, {"class": "noodles_pasta", "prob": "0.3267573"}, {"class": "seafood", "prob": "0.15450673"}, {"class": "egg", "prob": "0.030875659"}, {"class": "bread", "prob": "0.01638847"}, {"class": "vegetable_fruit", "prob": "0.01416823"}, {"class": "rice", "prob": "0.013158828"}, {"class": "soup", "prob": "0.0012706716"}, {"class": "fried_food", "prob": "0.00022045308"}, {"class": "dessert", "prob": "4.8754315e-05"}, {"class": "dairy_products", "prob": "7.2642297e-06"}]}