{"result_ingredients": [{"class": "powdered_sugar", "prob": "0.55077475"}, {"class": "sea_salt", "prob": "0.8052784"}, {"class": "coconut_oil", "prob": "0.78043425"}, {"class": "fat", "prob": "0.7249412"}], "result_recognition": [{"class": "sponge_cake", "prob": "0.7147165"}, {"class": "potatoes_with_garlic_and_parsley", "prob": "0.25659394"}, {"class": "fish_en_papillote", "prob": "0.0032231542"}, {"class": "grated_cauliflower", "prob": "0.002919919"}, {"class": "cabbage_with_potato_and_bacon", "prob": "0.0025809663"}], "img_url": "https://s3-media4.fl.yelpcdn.com/bphoto/FbjT-TtF9QHpfctCn2nFeQ/o.jpg", "img_path": "/media/HDD_2TB/LogMeal/api_dev//images/img_downloaded.jpg", "result_family": [{"class": "bread", "prob": "0.9922101"}, {"class": "vegetable_fruit", "prob": "0.0060986006"}, {"class": "seafood", "prob": "0.0012780589"}, {"class": "dessert", "prob": "0.00024821164"}, {"class": "fried_food", "prob": "7.427909e-05"}, {"class": "meat", "prob": "6.977349e-05"}, {"class": "soup", "prob": "1.8820856e-05"}, {"class": "noodles_pasta", "prob": "1.2660736e-06"}, {"class": "rice", "prob": "3.817114e-07"}, {"class": "dairy_products", "prob": "3.2551262e-07"}, {"class": "egg", "prob": "1.7784238e-07"}]}