{"result_ingredients": [{"class": "salt", "prob": "0.51799494"}, {"class": "eggs", "prob": "0.9515718"}, {"class": "sugar", "prob": "0.5552241"}, {"class": "water", "prob": "0.5122835"}], "result_recognition": [{"class": "samosa", "prob": "0.72546184"}, {"class": "dumplings", "prob": "0.17324889"}, {"class": "toasts_with_jam", "prob": "0.04525555"}, {"class": "chocolate_crepe", "prob": "0.010475556"}, {"class": "baklava", "prob": "0.006337848"}], "img_url": "https://s3-media2.fl.yelpcdn.com/bphoto/4vei3Q6WqCAG3APnrBOWqA/o.jpg", "img_path": "/media/HDD_2TB/LogMeal/api_rel//images/img_downloaded.jpg", "result_family": [{"class": "bread", "prob": "0.92892146"}, {"class": "dairy_products", "prob": "0.0364802"}, {"class": "dessert", "prob": "0.021905378"}, {"class": "egg", "prob": "0.0091320295"}, {"class": "fried_food", "prob": "0.0033075626"}, {"class": "meat", "prob": "0.000115123796"}, {"class": "seafood", "prob": "8.4763116e-05"}, {"class": "noodles_pasta", "prob": "1.614057e-05"}, {"class": "soup", "prob": "1.5841702e-05"}, {"class": "vegetable_fruit", "prob": "1.5257673e-05"}, {"class": "rice", "prob": "6.243603e-06"}]}