{"result_ingredients": [{"class": "salt", "prob": "0.88554"}, {"class": "eggs", "prob": "0.742436"}, {"class": "all-purpose_flour", "prob": "0.975882"}, {"class": "unsalted_butter", "prob": "0.811966"}, {"class": "milk", "prob": "0.757308"}, {"class": "vanilla_extract", "prob": "0.741757"}, {"class": "granulated_sugar", "prob": "0.93071"}, {"class": "powdered_sugar", "prob": "0.563277"}, {"class": "active_dry_yeast", "prob": "0.926414"}], "result_recognition": [{"class": "beignets", "prob": "0.869279"}, {"class": "cannoli", "prob": "0.11349"}, {"class": "sponge_cake", "prob": "0.00185084"}, {"class": "longaniza", "prob": "0.00160049"}, {"class": "spelt_bread", "prob": "0.00138566"}], "img_url": "https://s3-media1.fl.yelpcdn.com/bphoto/5le4yrwfkrKSyapQdyNw1g/o.jpg", "img_path": "/media/HDD_2TB/LogMeal/api_dev//images/img_downloaded.jpg", "result_family": [{"class": "dessert", "prob": "0.999266"}, {"class": "vegetable_fruit", "prob": "0.000595018"}, {"class": "seafood", "prob": "6.10436e-05"}, {"class": "bread", "prob": "2.40445e-05"}, {"class": "rice", "prob": "1.69417e-05"}, {"class": "meat", "prob": "1.48074e-05"}, {"class": "noodles_pasta", "prob": "7.76956e-06"}, {"class": "soup", "prob": "7.70194e-06"}, {"class": "egg", "prob": "4.26628e-06"}, {"class": "fried_food", "prob": "1.24433e-06"}, {"class": "dairy_products", "prob": "9.52067e-07"}]}