{"result_ingredients": [{"class": "salt", "prob": "0.859516"}, {"class": "all-purpose_flour", "prob": "0.992666"}, {"class": "unsalted_butter", "prob": "0.901455"}, {"class": "milk", "prob": "0.577498"}, {"class": "large_eggs", "prob": "0.812704"}, {"class": "vegetable_oil", "prob": "0.549617"}, {"class": "vanilla_extract", "prob": "0.823989"}, {"class": "granulated_sugar", "prob": "0.999721"}, {"class": "powdered_sugar", "prob": "0.997978"}, {"class": "whole_milk", "prob": "0.736568"}, {"class": "buttermilk", "prob": "0.781523"}, {"class": "active_dry_yeast", "prob": "0.998521"}], "result_recognition": [{"class": "beignets", "prob": "0.991966"}, {"class": "spelt_bread", "prob": "0.00410493"}, {"class": "donuts", "prob": "0.00315503"}, {"class": "sponge_cake", "prob": "0.0002113"}, {"class": "quince_with_cottage_cheese", "prob": "0.000174318"}], "img_url": "https://s3-media2.fl.yelpcdn.com/bphoto/_7QtWDJ-pX4aEHLIE85R8w/o.jpg", "img_path": "/media/HDD_2TB/LogMeal/api_dev//images/img_downloaded.jpg", "result_family": [{"class": "dessert", "prob": "0.999985"}, {"class": "seafood", "prob": "7.22077e-06"}, {"class": "fried_food", "prob": "2.70114e-06"}, {"class": "dairy_products", "prob": "1.35692e-06"}, {"class": "soup", "prob": "1.15125e-06"}, {"class": "meat", "prob": "9.85973e-07"}, {"class": "bread", "prob": "6.47773e-07"}, {"class": "noodles_pasta", "prob": "5.45699e-07"}, {"class": "egg", "prob": "1.68614e-07"}, {"class": "rice", "prob": "1.12612e-07"}, {"class": "vegetable_fruit", "prob": "8.53716e-08"}]}