{"result_ingredients": [{"class": "salt", "prob": "0.996588"}, {"class": "eggs", "prob": "0.972694"}, {"class": "sugar", "prob": "0.924265"}, {"class": "milk", "prob": "0.953296"}, {"class": "powdered_sugar", "prob": "0.997609"}, {"class": "active_dry_yeast", "prob": "0.989996"}], "result_recognition": [{"class": "beignets", "prob": "0.999991"}, {"class": "chocolate_truffles_with_cream", "prob": "4.66456e-06"}, {"class": "sponge_cake", "prob": "5.13275e-07"}, {"class": "quince_with_cottage_cheese", "prob": "5.01149e-07"}, {"class": "donuts", "prob": "4.59437e-07"}], "img_url": "https://s3-media2.fl.yelpcdn.com/bphoto/vU3_Mbl982tuBXwbtGdmSA/o.jpg", "img_path": "/media/HDD_2TB/LogMeal/api_dev//images/img_downloaded.jpg", "result_family": [{"class": "dessert", "prob": "1.0"}, {"class": "bread", "prob": "3.15069e-07"}, {"class": "dairy_products", "prob": "1.34339e-07"}, {"class": "egg", "prob": "1.02231e-08"}, {"class": "fried_food", "prob": "7.7694e-09"}, {"class": "noodles_pasta", "prob": "4.13529e-09"}, {"class": "meat", "prob": "3.76315e-09"}, {"class": "seafood", "prob": "2.74315e-09"}, {"class": "soup", "prob": "6.14199e-10"}, {"class": "rice", "prob": "2.37523e-10"}, {"class": "vegetable_fruit", "prob": "1.57642e-10"}]}