{"result_ingredients": [{"class": "salt", "prob": "0.864375"}, {"class": "all-purpose_flour", "prob": "0.892916"}, {"class": "unsalted_butter", "prob": "0.992698"}, {"class": "milk", "prob": "0.736509"}, {"class": "large_eggs", "prob": "0.563772"}, {"class": "vanilla_extract", "prob": "0.991745"}, {"class": "baking_powder", "prob": "0.532809"}, {"class": "granulated_sugar", "prob": "0.999199"}, {"class": "powdered_sugar", "prob": "0.867614"}, {"class": "baking_soda", "prob": "0.503198"}, {"class": "whole_milk", "prob": "0.929483"}, {"class": "light_brown_sugar", "prob": "0.714312"}, {"class": "active_dry_yeast", "prob": "0.672774"}], "result_recognition": [{"class": "spelt_bread", "prob": "0.379562"}, {"class": "beignets", "prob": "0.344253"}, {"class": "sponge_cake", "prob": "0.105173"}, {"class": "whole_grain_bread_with_olive_oil", "prob": "0.0748453"}, {"class": "wheat_gluten_with_vegetables", "prob": "0.0203154"}], "img_url": "https://s3-media1.fl.yelpcdn.com/bphoto/u6NZLCNuppO9dD3RbQ0KiA/o.jpg", "img_path": "/media/HDD_2TB/LogMeal/api_dev//images/img_downloaded.jpg", "result_family": [{"class": "seafood", "prob": "0.526766"}, {"class": "dessert", "prob": "0.46824"}, {"class": "egg", "prob": "0.00321749"}, {"class": "vegetable_fruit", "prob": "0.00134335"}, {"class": "rice", "prob": "0.000101462"}, {"class": "bread", "prob": "9.85331e-05"}, {"class": "noodles_pasta", "prob": "7.91857e-05"}, {"class": "fried_food", "prob": "6.85734e-05"}, {"class": "soup", "prob": "6.59483e-05"}, {"class": "meat", "prob": "1.92575e-05"}, {"class": "dairy_products", "prob": "5.79343e-07"}]}