{"result_ingredients": [{"class": "large_eggs", "prob": "0.889728"}, {"class": "vegetable_oil", "prob": "0.538902"}, {"class": "powdered_sugar", "prob": "0.655651"}], "result_recognition": [{"class": "creme_brulee", "prob": "0.738077"}, {"class": "foie_gras", "prob": "0.131895"}, {"class": "cheesecake", "prob": "0.0704665"}, {"class": "panna_cotta", "prob": "0.0396266"}, {"class": "toasts_with_jam", "prob": "0.00707033"}], "img_url": "https://s3-media3.fl.yelpcdn.com/bphoto/MHJY22_RRMjanIXd6q6Bdw/o.jpg", "img_path": "/media/HDD_2TB/LogMeal/api_dev//images/img_downloaded.jpg", "result_family": [{"class": "dessert", "prob": "0.954948"}, {"class": "fried_food", "prob": "0.0317936"}, {"class": "bread", "prob": "0.00574815"}, {"class": "seafood", "prob": "0.00441709"}, {"class": "dairy_products", "prob": "0.0019981"}, {"class": "meat", "prob": "0.00082742"}, {"class": "vegetable_fruit", "prob": "0.000209523"}, {"class": "soup", "prob": "3.71379e-05"}, {"class": "noodles_pasta", "prob": "1.0985e-05"}, {"class": "rice", "prob": "8.15845e-06"}, {"class": "egg", "prob": "2.13617e-06"}]}