{"result_ingredients": [{"class": "sesame_oil", "prob": "0.647432"}], "result_recognition": [{"class": "sole_with_onion", "prob": "0.444718"}, {"class": "catalonian_spinach", "prob": "0.10996"}, {"class": "omelette", "prob": "0.0912276"}, {"class": "breaded_cod", "prob": "0.080552"}, {"class": "white_beans_with_spinach", "prob": "0.029031"}], "img_url": "https://s3-media1.fl.yelpcdn.com/bphoto/Dudr6i_ZbwAWloFG7wyUgg/o.jpg", "img_path": "/media/HDD_2TB/LogMeal/api_dev//images/img_downloaded.jpg", "result_family": [{"class": "seafood", "prob": "0.87728"}, {"class": "soup", "prob": "0.0720246"}, {"class": "vegetable_fruit", "prob": "0.0241543"}, {"class": "rice", "prob": "0.0145986"}, {"class": "meat", "prob": "0.00570344"}, {"class": "noodles_pasta", "prob": "0.00301508"}, {"class": "egg", "prob": "0.00249373"}, {"class": "bread", "prob": "0.000606062"}, {"class": "fried_food", "prob": "8.40011e-05"}, {"class": "dessert", "prob": "4.01643e-05"}, {"class": "dairy_products", "prob": "2.13011e-07"}]}