{"result_foodtypes": [{"output": {"labels": ["non_food", "food", "ingredients", "drinks"], "probs": [3.172717129018565e-07, 0.9875444173812866, 0.012358998879790306, 9.62715785135515e-05]}}], "img_path": "/media/HDD_2TB/LogMeal/api_rel//images/img_downloaded.jpg", "result_recognition": [{"class": "hamburger", "prob": "0.65511996"}, {"class": "escargots", "prob": "0.18911237"}, {"class": "bread_with_tomato_and_ham", "prob": "0.021450944"}, {"class": "sauteed_mushrooms", "prob": "0.015992112"}, {"class": "blood_sausage", "prob": "0.015944652"}], "result_ingredients": [{"class": "ground_beef", "prob": "0.5476559"}], "img_url": "https://s3-media1.fl.yelpcdn.com/bphoto/4-hkOnVceckI5irKRm8bmg/o.jpg", "result_family": [{"class": "bread", "prob": "0.95925593"}, {"class": "seafood", "prob": "0.039065313"}, {"class": "vegetable_fruit", "prob": "0.0009989796"}, {"class": "meat", "prob": "0.00051238603"}, {"class": "egg", "prob": "7.953291e-05"}, {"class": "soup", "prob": "5.8843947e-05"}, {"class": "fried_food", "prob": "1.48314575e-05"}, {"class": "dessert", "prob": "9.728841e-06"}, {"class": "rice", "prob": "4.0449427e-06"}, {"class": "dairy_products", "prob": "2.7801292e-07"}, {"class": "noodles_pasta", "prob": "1.3633311e-07"}]}