{"result_ingredients": [{"class": "heavy_cream", "prob": "0.66359293"}], "result_recognition": [{"class": "deviled_eggs", "prob": "0.9993667"}, {"class": "endive_Salad", "prob": "0.00022088172"}, {"class": "strawberries_and_cream", "prob": "0.0001163875"}, {"class": "grilled_cuttlefish", "prob": "3.707211e-05"}, {"class": "waffles", "prob": "3.4815763e-05"}], "img_url": "https://s3-media3.fl.yelpcdn.com/bphoto/paWXukutY4UOhTR3mqRRpw/o.jpg", "img_path": "/media/HDD_2TB/LogMeal/api_rel//images/img_downloaded.jpg", "result_family": [{"class": "egg", "prob": "0.9999997"}, {"class": "fried_food", "prob": "1.6672159e-07"}, {"class": "dessert", "prob": "7.0107745e-08"}, {"class": "seafood", "prob": "1.9565265e-08"}, {"class": "soup", "prob": "9.557835e-09"}, {"class": "vegetable_fruit", "prob": "3.3583876e-09"}, {"class": "bread", "prob": "2.2587523e-09"}, {"class": "dairy_products", "prob": "1.8531607e-09"}, {"class": "meat", "prob": "9.2321756e-10"}, {"class": "noodles_pasta", "prob": "1.9588918e-10"}, {"class": "rice", "prob": "1.2161505e-10"}]}