{"result_ingredients": [{"class": "salt", "prob": "0.74892455"}, {"class": "water", "prob": "0.74751616"}, {"class": "flour", "prob": "0.759409"}, {"class": "corn_starch", "prob": "0.91079056"}, {"class": "ground_cumin", "prob": "0.7050201"}, {"class": "frozen_peas", "prob": "0.76185614"}, {"class": "warm_water", "prob": "0.7169243"}], "result_recognition": [{"class": "garlic_bread", "prob": "0.37196004"}, {"class": "samosa", "prob": "0.22474182"}, {"class": "dumplings", "prob": "0.18180543"}, {"class": "beignets", "prob": "0.053589787"}, {"class": "takoyaki", "prob": "0.03036042"}], "img_url": "https://s3-media4.fl.yelpcdn.com/bphoto/47B1Qs0Fk3UzKuRa4g7Q_w/o.jpg", "img_path": "/media/HDD_2TB/LogMeal/api_dev//images/img_downloaded.jpg", "result_family": [{"class": "fried_food", "prob": "0.9758814"}, {"class": "dessert", "prob": "0.023308368"}, {"class": "seafood", "prob": "0.00076185854"}, {"class": "bread", "prob": "2.6799804e-05"}, {"class": "meat", "prob": "1.4052977e-05"}, {"class": "vegetable_fruit", "prob": "3.2064477e-06"}, {"class": "soup", "prob": "2.5141737e-06"}, {"class": "noodles_pasta", "prob": "9.872292e-07"}, {"class": "egg", "prob": "6.3917327e-07"}, {"class": "dairy_products", "prob": "1.5237016e-07"}, {"class": "rice", "prob": "3.7647638e-08"}]}