{"result_ingredients": [{"class": "salt", "prob": "0.999882"}, {"class": "eggs", "prob": "0.981921"}, {"class": "sugar", "prob": "0.989393"}, {"class": "powdered_sugar", "prob": "0.999994"}, {"class": "oil", "prob": "0.969929"}, {"class": "warm_water", "prob": "0.987621"}, {"class": "active_dry_yeast", "prob": "0.999938"}, {"class": "evaporated_milk", "prob": "0.707973"}, {"class": "yeast", "prob": "0.847249"}], "result_recognition": [{"class": "beignets", "prob": "0.999989"}, {"class": "donuts", "prob": "1.07306e-05"}, {"class": "sponge_cake", "prob": "2.3241e-07"}, {"class": "onion_rings", "prob": "2.16969e-07"}, {"class": "churros", "prob": "5.25053e-08"}], "img_url": "https://s3-media1.fl.yelpcdn.com/bphoto/mDKUMoCfmYPS2rIqDSV6_g/o.jpg", "img_path": "/media/HDD_2TB/LogMeal/api_dev//images/img_downloaded.jpg", "result_family": [{"class": "dessert", "prob": "0.990051"}, {"class": "meat", "prob": "0.00824295"}, {"class": "dairy_products", "prob": "0.00111238"}, {"class": "bread", "prob": "0.00031881"}, {"class": "fried_food", "prob": "0.000210165"}, {"class": "rice", "prob": "3.97468e-05"}, {"class": "vegetable_fruit", "prob": "2.05582e-05"}, {"class": "seafood", "prob": "2.02617e-06"}, {"class": "egg", "prob": "1.09113e-06"}, {"class": "soup", "prob": "7.35492e-07"}, {"class": "noodles_pasta", "prob": "7.32553e-08"}]}