{"result_ingredients": [{"class": "chives", "prob": "0.540161"}, {"class": "foie_gras", "prob": "0.822969"}, {"class": "sea_scallops", "prob": "0.884419"}], "result_recognition": [{"class": "scallops", "prob": "0.999998"}, {"class": "foie_gras", "prob": "2.24498e-06"}, {"class": "shrimp_and_grits", "prob": "6.57411e-10"}, {"class": "bread_pudding", "prob": "3.53178e-10"}, {"class": "cheesecake", "prob": "2.93048e-10"}], "img_url": "https://s3-media4.fl.yelpcdn.com/bphoto/B-Gpd97L09HE-vmLSe9fmQ/o.jpg", "img_path": "/media/HDD_2TB/LogMeal/api_dev//images/img_downloaded.jpg", "result_family": [{"class": "seafood", "prob": "0.996296"}, {"class": "meat", "prob": "0.00370051"}, {"class": "bread", "prob": "3.02606e-06"}, {"class": "rice", "prob": "5.61292e-07"}, {"class": "vegetable_fruit", "prob": "1.67666e-07"}, {"class": "noodles_pasta", "prob": "5.85436e-08"}, {"class": "soup", "prob": "4.90207e-08"}, {"class": "dessert", "prob": "1.75751e-08"}, {"class": "egg", "prob": "2.85293e-09"}, {"class": "dairy_products", "prob": "2.02379e-09"}, {"class": "fried_food", "prob": "1.78851e-10"}]}