{"result_ingredients": [{"class": "kosher_salt", "prob": "0.935088"}, {"class": "sea_scallops", "prob": "1.0"}], "result_recognition": [{"class": "scallops", "prob": "0.996758"}, {"class": "grilled_cuttlefish", "prob": "0.00214793"}, {"class": "crab_cakes", "prob": "0.000140072"}, {"class": "cottage_cheese_with_honey", "prob": "0.000118008"}, {"class": "breaded_cod", "prob": "0.000110395"}], "img_url": "https://s3-media2.fl.yelpcdn.com/bphoto/g4yq4MhtaiE-BaCPC5BDLA/o.jpg", "img_path": "/media/HDD_2TB/LogMeal/api_dev//images/img_downloaded.jpg", "result_family": [{"class": "seafood", "prob": "0.999998"}, {"class": "soup", "prob": "1.95429e-06"}, {"class": "dessert", "prob": "8.06675e-08"}, {"class": "rice", "prob": "5.94908e-08"}, {"class": "meat", "prob": "5.45782e-08"}, {"class": "noodles_pasta", "prob": "3.33423e-08"}, {"class": "vegetable_fruit", "prob": "2.93782e-08"}, {"class": "egg", "prob": "6.06754e-09"}, {"class": "fried_food", "prob": "3.66447e-09"}, {"class": "bread", "prob": "1.34765e-09"}, {"class": "dairy_products", "prob": "9.26712e-12"}]}