{"result_foodtypes": [{"output": {"labels": ["non_food", "food", "ingredients", "drinks"], "probs": [2.2970299085045554e-07, 0.9969027638435364, 0.0030779708176851273, 1.9034385331906378e-05]}}], "img_path": "/media/HDD_2TB/LogMeal/api_rel//images/img_downloaded.jpg", "result_recognition": [{"class": "filet_mignon", "prob": "0.29996955"}, {"class": "blood_sausage", "prob": "0.18152936"}, {"class": "risotto", "prob": "0.15432681"}, {"class": "guacamole", "prob": "0.14306912"}, {"class": "hamburger", "prob": "0.02900358"}], "result_ingredients": [{"class": "vegetable_oil", "prob": "0.60625637"}, {"class": "chives", "prob": "0.5382767"}, {"class": "old_bay_seasoning", "prob": "0.55306226"}], "img_url": "https://s3-media2.fl.yelpcdn.com/bphoto/hPCo-TIckFzKCT5jZ1_ofA/o.jpg", "result_family": [{"class": "rice", "prob": "0.98246044"}, {"class": "vegetable_fruit", "prob": "0.0073198983"}, {"class": "seafood", "prob": "0.0053136917"}, {"class": "noodles_pasta", "prob": "0.0045636613"}, {"class": "bread", "prob": "0.00024558057"}, {"class": "meat", "prob": "5.9165155e-05"}, {"class": "egg", "prob": "2.272892e-05"}, {"class": "soup", "prob": "8.241603e-06"}, {"class": "fried_food", "prob": "5.2356095e-06"}, {"class": "dessert", "prob": "1.3471032e-06"}, {"class": "dairy_products", "prob": "6.589538e-09"}]}