{"result_ingredients": [{"class": "salt", "prob": "0.68110824"}, {"class": "olive_oil", "prob": "0.79490125"}, {"class": "garlic", "prob": "0.53802073"}], "result_recognition": [{"class": "chorizo", "prob": "0.24127932"}, {"class": "white_bean_with_cod", "prob": "0.22134797"}, {"class": "sauteed_vegetables", "prob": "0.07023685"}, {"class": "grilled_tofu", "prob": "0.045541134"}, {"class": "riojan-style_potatoes", "prob": "0.044555616"}], "img_url": "https://s3-media2.fl.yelpcdn.com/bphoto/zKb9_Edy-pst2q_S7SAfcA/o.jpg", "img_path": "/media/HDD_2TB/LogMeal/api_rel//images/img_downloaded.jpg", "result_family": [{"class": "vegetable_fruit", "prob": "0.8414962"}, {"class": "meat", "prob": "0.1304056"}, {"class": "noodles_pasta", "prob": "0.009800279"}, {"class": "soup", "prob": "0.006289171"}, {"class": "fried_food", "prob": "0.0034748185"}, {"class": "bread", "prob": "0.002978246"}, {"class": "egg", "prob": "0.0029017888"}, {"class": "rice", "prob": "0.0019024045"}, {"class": "seafood", "prob": "0.00063783425"}, {"class": "dessert", "prob": "5.8789894e-05"}, {"class": "dairy_products", "prob": "5.4829357e-05"}]}