{"result_ingredients": [{"class": "eggs", "prob": "0.919537"}, {"class": "sugar", "prob": "0.702836"}], "result_recognition": [{"class": "cuban-style_rice", "prob": "0.241217"}, {"class": "yogurt", "prob": "0.205881"}, {"class": "white_bean_with_cod", "prob": "0.0786156"}, {"class": "clam_chowder", "prob": "0.0747318"}, {"class": "garlic_soup", "prob": "0.0480172"}], "img_url": "https://s3-media3.fl.yelpcdn.com/bphoto/5JCLgQgVtejS73kJxcif_w/o.jpg", "img_path": "/media/HDD_2TB/LogMeal/api_dev//images/img_downloaded.jpg", "result_family": [{"class": "seafood", "prob": "0.589521"}, {"class": "rice", "prob": "0.128079"}, {"class": "vegetable_fruit", "prob": "0.109948"}, {"class": "bread", "prob": "0.0522315"}, {"class": "dessert", "prob": "0.0497681"}, {"class": "meat", "prob": "0.0472647"}, {"class": "egg", "prob": "0.017882"}, {"class": "fried_food", "prob": "0.00328499"}, {"class": "noodles_pasta", "prob": "0.0014805"}, {"class": "soup", "prob": "0.0005198"}, {"class": "dairy_products", "prob": "2.09764e-05"}]}