{"result_ingredients": [{"class": "eggs", "prob": "0.785273"}, {"class": "butter", "prob": "0.643158"}, {"class": "baking_soda", "prob": "0.990434"}, {"class": "vanilla", "prob": "0.912132"}, {"class": "buttermilk", "prob": "0.983034"}, {"class": "cocoa_powder", "prob": "0.797037"}], "result_recognition": [{"class": "grilled_tofu", "prob": "0.994255"}, {"class": "sponge_cake", "prob": "0.00519537"}, {"class": "chorizo", "prob": "0.000184985"}, {"class": "chistorra", "prob": "7.05852e-05"}, {"class": "tuna_tataki", "prob": "6.39758e-05"}], "img_url": "https://s3-media1.fl.yelpcdn.com/bphoto/4GCp0v7h2BJUGO4aRW-8zQ/o.jpg", "img_path": "/media/HDD_2TB/LogMeal/api_dev//images/img_downloaded.jpg", "result_family": [{"class": "dessert", "prob": "0.99439"}, {"class": "vegetable_fruit", "prob": "0.00255309"}, {"class": "dairy_products", "prob": "0.00175746"}, {"class": "fried_food", "prob": "0.0012973"}, {"class": "meat", "prob": "2.0256e-06"}, {"class": "seafood", "prob": "1.75623e-07"}, {"class": "noodles_pasta", "prob": "1.5852e-07"}, {"class": "soup", "prob": "2.12595e-08"}, {"class": "bread", "prob": "3.10677e-09"}, {"class": "rice", "prob": "7.44737e-10"}, {"class": "egg", "prob": "3.22865e-11"}]}