{"result_ingredients": [{"class": "olive_oil", "prob": "0.51215434"}, {"class": "extra-virgin_olive_oil", "prob": "0.5120177"}, {"class": "fresh_basil_leaves", "prob": "0.85119283"}], "result_recognition": [{"class": "lobster_bisque", "prob": "0.1216505"}, {"class": "risotto", "prob": "0.06081027"}, {"class": "ice_cream", "prob": "0.05053226"}, {"class": "jelly", "prob": "0.050231133"}, {"class": "hot_dog", "prob": "0.04454839"}], "img_url": "https://s3-media3.fl.yelpcdn.com/bphoto/jI5S9sOVyUMLCxb0LPL2MQ/o.jpg", "img_path": "/media/HDD_2TB/LogMeal/api_rel//images/img_downloaded.jpg", "result_family": [{"class": "dessert", "prob": "0.74681294"}, {"class": "vegetable_fruit", "prob": "0.108979784"}, {"class": "seafood", "prob": "0.10572728"}, {"class": "meat", "prob": "0.015753005"}, {"class": "soup", "prob": "0.00682543"}, {"class": "bread", "prob": "0.0055233994"}, {"class": "fried_food", "prob": "0.00535104"}, {"class": "egg", "prob": "0.0025247133"}, {"class": "dairy_products", "prob": "0.0017699986"}, {"class": "rice", "prob": "0.00066311925"}, {"class": "noodles_pasta", "prob": "6.92874e-05"}]}