{"result_ingredients": [], "result_recognition": [{"class": "risotto", "prob": "0.7714162"}, {"class": "paella", "prob": "0.12437707"}, {"class": "omelette", "prob": "0.024141012"}, {"class": "fried_rice", "prob": "0.021892464"}, {"class": "shrimp_and_grits", "prob": "0.017162021"}], "img_url": "https://s3-media2.fl.yelpcdn.com/bphoto/LX-B3f-zQMQ2fgoJKwNHjg/o.jpg", "img_path": "/media/HDD_2TB/LogMeal/api_dev//images/img_downloaded.jpg", "result_family": [{"class": "rice", "prob": "0.9998606"}, {"class": "seafood", "prob": "0.00012545857"}, {"class": "meat", "prob": "1.16311885e-05"}, {"class": "noodles_pasta", "prob": "1.278719e-06"}, {"class": "vegetable_fruit", "prob": "4.1632748e-07"}, {"class": "soup", "prob": "2.9513004e-07"}, {"class": "fried_food", "prob": "1.8954239e-07"}, {"class": "egg", "prob": "1.297361e-07"}, {"class": "bread", "prob": "2.0416728e-08"}, {"class": "dessert", "prob": "9.4664776e-11"}, {"class": "dairy_products", "prob": "1.7044479e-11"}]}