{"result_ingredients": [{"class": "salt", "prob": "0.76714927"}, {"class": "sugar", "prob": "0.95848686"}, {"class": "all-purpose_flour", "prob": "0.9048858"}, {"class": "baking_powder", "prob": "0.93990785"}], "result_recognition": [{"class": "pancakes", "prob": "0.95236844"}, {"class": "fruit_crepe", "prob": "0.039626732"}, {"class": "omelette", "prob": "0.005607133"}, {"class": "chocolate_crepe", "prob": "0.0015032758"}, {"class": "huevos_rancheros", "prob": "0.0007482468"}], "img_url": "https://s3-media2.fl.yelpcdn.com/bphoto/iKHbz6RwWt2DXhvAp10pvA/o.jpg", "img_path": "/media/HDD_2TB/LogMeal/api_rel//images/img_downloaded.jpg", "result_family": [{"class": "dessert", "prob": "0.9999497"}, {"class": "egg", "prob": "3.120637e-05"}, {"class": "bread", "prob": "1.4612916e-05"}, {"class": "noodles_pasta", "prob": "1.7214733e-06"}, {"class": "dairy_products", "prob": "1.1091065e-06"}, {"class": "meat", "prob": "8.764589e-07"}, {"class": "fried_food", "prob": "4.1720963e-07"}, {"class": "vegetable_fruit", "prob": "1.9131605e-07"}, {"class": "seafood", "prob": "1.4226337e-07"}, {"class": "soup", "prob": "2.1711026e-08"}, {"class": "rice", "prob": "1.8548372e-08"}]}