{"result_ingredients": [{"class": "cilantro", "prob": "0.69961363"}, {"class": "nori", "prob": "0.6714526"}, {"class": "star_anise", "prob": "0.9395531"}, {"class": "coriander_seeds", "prob": "0.8923471"}, {"class": "mung_bean_sprouts", "prob": "0.7113058"}], "result_recognition": [{"class": "salad_with_seeds", "prob": "0.23732127"}, {"class": "fermented_cabbage", "prob": "0.15127413"}, {"class": "curry_noodles_with_mushrooms", "prob": "0.08828177"}, {"class": "bibimbap", "prob": "0.06856321"}, {"class": "ice_cream", "prob": "0.061105765"}], "img_url": "https://s3-media3.fl.yelpcdn.com/bphoto/gfuWujetfEk4YHqMCvYRWw/o.jpg", "img_path": "/media/HDD_2TB/LogMeal/api_rel//images/img_downloaded.jpg", "result_family": [{"class": "vegetable_fruit", "prob": "0.7008516"}, {"class": "soup", "prob": "0.24086271"}, {"class": "seafood", "prob": "0.027092114"}, {"class": "meat", "prob": "0.017538434"}, {"class": "egg", "prob": "0.0052756863"}, {"class": "noodles_pasta", "prob": "0.00473416"}, {"class": "fried_food", "prob": "0.003161071"}, {"class": "bread", "prob": "0.00019653111"}, {"class": "rice", "prob": "0.00012901357"}, {"class": "dairy_products", "prob": "0.00010785564"}, {"class": "dessert", "prob": "5.0826075e-05"}]}