{"result_ingredients": [], "result_recognition": [{"class": "carrot_cake", "prob": "0.26118588"}, {"class": "frozen_yogurt", "prob": "0.13132493"}, {"class": "porridge_with_apple_and_cinnamon", "prob": "0.09650515"}, {"class": "chocolate_mousse", "prob": "0.0924156"}, {"class": "cottage_cheese_with_honey", "prob": "0.060867243"}], "img_url": "https://s3-media2.fl.yelpcdn.com/bphoto/PCDyYLjvA6IzJ5QbaAo4Bw/o.jpg", "img_path": "/media/HDD_2TB/LogMeal/api_dev//images/img_downloaded.jpg", "result_family": [{"class": "dessert", "prob": "0.95563453"}, {"class": "meat", "prob": "0.018252868"}, {"class": "rice", "prob": "0.016040338"}, {"class": "noodles_pasta", "prob": "0.004917691"}, {"class": "seafood", "prob": "0.0014203208"}, {"class": "egg", "prob": "0.0012430531"}, {"class": "fried_food", "prob": "0.001019475"}, {"class": "vegetable_fruit", "prob": "0.00071354734"}, {"class": "dairy_products", "prob": "0.0004877634"}, {"class": "soup", "prob": "0.0001744879"}, {"class": "bread", "prob": "9.594607e-05"}]}