{"result_ingredients": [], "result_recognition": [{"class": "chocolate_mousse", "prob": "0.450173"}, {"class": "chocolate_cake", "prob": "0.297525"}, {"class": "carrot_cake", "prob": "0.0720717"}, {"class": "bread_pudding", "prob": "0.0451089"}, {"class": "cottage_cheese_with_honey", "prob": "0.0248919"}], "img_url": "https://s3-media1.fl.yelpcdn.com/bphoto/5EXsLYeaTIOWHGyPynY4Dg/o.jpg", "img_path": "/media/HDD_2TB/LogMeal/api_dev//images/img_downloaded.jpg", "result_family": [{"class": "dessert", "prob": "0.999471"}, {"class": "meat", "prob": "0.000394551"}, {"class": "dairy_products", "prob": "3.71545e-05"}, {"class": "rice", "prob": "3.56807e-05"}, {"class": "fried_food", "prob": "3.32417e-05"}, {"class": "vegetable_fruit", "prob": "1.6484e-05"}, {"class": "seafood", "prob": "1.2108e-05"}, {"class": "soup", "prob": "8.60985e-08"}, {"class": "bread", "prob": "2.39321e-08"}, {"class": "egg", "prob": "1.23992e-08"}, {"class": "noodles_pasta", "prob": "6.43727e-09"}]}