{"result_ingredients": [{"class": "salt", "prob": "0.9657021"}, {"class": "butter", "prob": "0.9394314"}, {"class": "sugar", "prob": "0.7236664"}, {"class": "nutmeg", "prob": "0.9258909"}], "result_recognition": [{"class": "risotto", "prob": "0.31149897"}, {"class": "garlic_soup", "prob": "0.24686593"}, {"class": "cabbage_with_potato_and_bacon", "prob": "0.07446041"}, {"class": "macaroni_and_cheese", "prob": "0.06482804"}, {"class": "creme_brulee", "prob": "0.046455786"}], "img_url": "https://s3-media2.fl.yelpcdn.com/bphoto/2v_SYY87HAD0NuCXVKkBBA/o.jpg", "img_path": "/media/HDD_2TB/LogMeal/api_dev//images/img_downloaded.jpg", "result_family": [{"class": "noodles_pasta", "prob": "0.69314057"}, {"class": "fried_food", "prob": "0.11315033"}, {"class": "soup", "prob": "0.095465176"}, {"class": "meat", "prob": "0.0605355"}, {"class": "seafood", "prob": "0.023698855"}, {"class": "bread", "prob": "0.004771913"}, {"class": "dessert", "prob": "0.0030396106"}, {"class": "egg", "prob": "0.0030090683"}, {"class": "rice", "prob": "0.0027867071"}, {"class": "vegetable_fruit", "prob": "0.00037252117"}, {"class": "dairy_products", "prob": "2.9767905e-05"}]}