{"result_ingredients": [{"class": "salt", "prob": "0.566917"}, {"class": "olive_oil", "prob": "0.749866"}, {"class": "unsalted_butter", "prob": "0.754289"}, {"class": "extra-virgin_olive_oil", "prob": "0.54261"}, {"class": "chives", "prob": "0.739426"}], "result_recognition": [{"class": "risotto", "prob": "0.966186"}, {"class": "lentils_with_chorizo", "prob": "0.00786697"}, {"class": "pea_soup", "prob": "0.0058031"}, {"class": "hake_with_green_sauce", "prob": "0.00508097"}, {"class": "longaniza", "prob": "0.00446282"}], "img_url": "https://s3-media1.fl.yelpcdn.com/bphoto/4UveAuOV2eISG8-QJAqWew/o.jpg", "img_path": "/media/HDD_2TB/LogMeal/api_dev//images/img_downloaded.jpg", "result_family": [{"class": "rice", "prob": "0.999936"}, {"class": "seafood", "prob": "4.88991e-05"}, {"class": "soup", "prob": "1.43945e-05"}, {"class": "noodles_pasta", "prob": "2.78218e-07"}, {"class": "meat", "prob": "1.99715e-07"}, {"class": "vegetable_fruit", "prob": "1.7127e-08"}, {"class": "egg", "prob": "1.85411e-09"}, {"class": "dessert", "prob": "2.97155e-11"}, {"class": "bread", "prob": "2.77823e-11"}, {"class": "dairy_products", "prob": "1.1621e-12"}, {"class": "fried_food", "prob": "7.43468e-13"}]}