{"result_ingredients": [{"class": "onions", "prob": "0.680086"}, {"class": "unsalted_butter", "prob": "0.94401"}, {"class": "parmesan_cheese", "prob": "0.817847"}, {"class": "half_&_half", "prob": "0.809555"}], "result_recognition": [{"class": "risotto", "prob": "0.985248"}, {"class": "macaroni_and_cheese", "prob": "0.00300542"}, {"class": "ravioli", "prob": "0.00237575"}, {"class": "white_bean_with_cod", "prob": "0.00160541"}, {"class": "salmon_and_avocado_Tartar", "prob": "0.00139187"}], "img_url": "https://s3-media3.fl.yelpcdn.com/bphoto/MP0UZSulmojvNJ0k4V8USw/o.jpg", "img_path": "/media/HDD_2TB/LogMeal/api_dev//images/img_downloaded.jpg", "result_family": [{"class": "rice", "prob": "0.999888"}, {"class": "noodles_pasta", "prob": "0.000101302"}, {"class": "soup", "prob": "1.09923e-05"}, {"class": "seafood", "prob": "1.63845e-07"}, {"class": "vegetable_fruit", "prob": "9.30411e-09"}, {"class": "meat", "prob": "7.37268e-09"}, {"class": "bread", "prob": "5.23229e-11"}, {"class": "egg", "prob": "2.48189e-11"}, {"class": "fried_food", "prob": "2.25996e-12"}, {"class": "dessert", "prob": "1.98483e-12"}, {"class": "dairy_products", "prob": "2.48931e-14"}]}