{"result_ingredients": [{"class": "eggs", "prob": "0.99007237"}, {"class": "butter", "prob": "0.71601486"}, {"class": "water", "prob": "0.73540634"}, {"class": "lemon_juice", "prob": "0.5973471"}, {"class": "egg_yolks", "prob": "0.99725246"}, {"class": "white_vinegar", "prob": "0.8700472"}, {"class": "cayenne", "prob": "0.59498507"}, {"class": "english_muffins", "prob": "0.9384097"}], "result_recognition": [{"class": "eggs_benedict", "prob": "0.98750335"}, {"class": "beef_tartare", "prob": "0.0026154045"}, {"class": "asparagus_with_ham", "prob": "0.0017573134"}, {"class": "toasts_with_smoked_salmon", "prob": "0.0006707651"}, {"class": "sauteed_spinach_with_prawns", "prob": "0.0006260312"}], "img_url": "https://s3-media2.fl.yelpcdn.com/bphoto/QNl-o0gcVBl-D0bAUeXmtg/o.jpg", "img_path": "/media/HDD_2TB/LogMeal/api_rel//images/img_downloaded.jpg", "result_family": [{"class": "vegetable_fruit", "prob": "0.49148342"}, {"class": "egg", "prob": "0.39694777"}, {"class": "soup", "prob": "0.09517408"}, {"class": "noodles_pasta", "prob": "0.0072207768"}, {"class": "meat", "prob": "0.0033717281"}, {"class": "rice", "prob": "0.0026335071"}, {"class": "seafood", "prob": "0.002107897"}, {"class": "fried_food", "prob": "0.00042177647"}, {"class": "bread", "prob": "0.00032745767"}, {"class": "dairy_products", "prob": "0.0002378124"}, {"class": "dessert", "prob": "7.378799e-05"}]}