{"result_ingredients": [{"class": "unsalted_butter", "prob": "0.66343427"}], "result_recognition": [{"class": "roasted_suckling_pig", "prob": "0.52118033"}, {"class": "dark_chocolate", "prob": "0.087379016"}, {"class": "beignets", "prob": "0.063993"}, {"class": "grilled_turkey", "prob": "0.04725823"}, {"class": "whole_grain_bread_with_olive_oil", "prob": "0.044300538"}], "img_url": "https://s3-media2.fl.yelpcdn.com/bphoto/0k-JhAUy6NYk_TmwXjXThA/o.jpg", "img_path": "/media/HDD_2TB/LogMeal/api_dev//images/img_downloaded.jpg", "result_family": [{"class": "meat", "prob": "0.3506285"}, {"class": "dessert", "prob": "0.3187889"}, {"class": "seafood", "prob": "0.17975341"}, {"class": "fried_food", "prob": "0.13174413"}, {"class": "soup", "prob": "0.0139148"}, {"class": "bread", "prob": "0.0035377217"}, {"class": "egg", "prob": "0.0008134246"}, {"class": "vegetable_fruit", "prob": "0.00054212613"}, {"class": "rice", "prob": "0.00017506388"}, {"class": "noodles_pasta", "prob": "7.5188946e-05"}, {"class": "dairy_products", "prob": "2.6746036e-05"}]}