{"result_ingredients": [{"class": "rice_vinegar", "prob": "0.62260157"}], "result_recognition": [{"class": "whole_grain_bread_with_olive_oil", "prob": "0.21269868"}, {"class": "patatas_bravas", "prob": "0.12188925"}, {"class": "sponge_cake", "prob": "0.11245564"}, {"class": "pea_soup", "prob": "0.10321173"}, {"class": "sheep_milk_cheese", "prob": "0.07681164"}], "img_url": "https://s3-media4.fl.yelpcdn.com/bphoto/oPw7p2Gfy5H86abzJzNVKA/o.jpg", "img_path": "/media/HDD_2TB/LogMeal/api_dev//images/img_downloaded.jpg", "result_family": [{"class": "seafood", "prob": "0.68582684"}, {"class": "meat", "prob": "0.12407409"}, {"class": "vegetable_fruit", "prob": "0.123415306"}, {"class": "fried_food", "prob": "0.025558898"}, {"class": "bread", "prob": "0.014338445"}, {"class": "soup", "prob": "0.010620956"}, {"class": "egg", "prob": "0.005274866"}, {"class": "dessert", "prob": "0.0043526404"}, {"class": "dairy_products", "prob": "0.0025990752"}, {"class": "noodles_pasta", "prob": "0.0024900264"}, {"class": "rice", "prob": "0.0014488543"}]}