{"result_ingredients": [{"class": "pepper", "prob": "0.964027"}, {"class": "cheese", "prob": "0.773929"}], "result_recognition": [{"class": "chorizo", "prob": "0.9893829"}, {"class": "omelette", "prob": "0.0035326078"}, {"class": "cabbage_with_potato_and_bacon", "prob": "0.0032282858"}, {"class": "zucchini_Omelet", "prob": "0.0004037155"}, {"class": "chistorra", "prob": "0.00030723735"}], "img_url": "https://s3-media4.fl.yelpcdn.com/bphoto/Q6ezIHl_rEKtIy47IADZAw/o.jpg", "img_path": "/media/HDD_2TB/LogMeal/api_rel//images/img_downloaded.jpg", "result_family": [{"class": "fried_food", "prob": "0.8947158"}, {"class": "meat", "prob": "0.052862562"}, {"class": "egg", "prob": "0.04554205"}, {"class": "seafood", "prob": "0.005051226"}, {"class": "vegetable_fruit", "prob": "0.0011803283"}, {"class": "bread", "prob": "0.00035876312"}, {"class": "rice", "prob": "0.00028017053"}, {"class": "soup", "prob": "4.77429e-06"}, {"class": "dessert", "prob": "3.6033423e-06"}, {"class": "noodles_pasta", "prob": "5.285386e-07"}, {"class": "dairy_products", "prob": "2.3308243e-07"}]}