{"result_ingredients": [{"class": "kosher_salt", "prob": "0.6735512"}, {"class": "bay_leaves", "prob": "0.6034386"}, {"class": "melted_butter", "prob": "0.6457514"}], "result_recognition": [{"class": "foie_gras", "prob": "0.22405566"}, {"class": "garlic_soup", "prob": "0.12994966"}, {"class": "patatas_bravas", "prob": "0.09773021"}, {"class": "lobster_bisque", "prob": "0.073582076"}, {"class": "tuna_tartare", "prob": "0.071919344"}], "img_url": "https://s3-media4.fl.yelpcdn.com/bphoto/fKNOJbP_TIKcCWoh8Kxy-g/o.jpg", "img_path": "/media/HDD_2TB/LogMeal/api_dev//images/img_downloaded.jpg", "result_family": [{"class": "seafood", "prob": "0.9075023"}, {"class": "meat", "prob": "0.04170581"}, {"class": "fried_food", "prob": "0.036030907"}, {"class": "soup", "prob": "0.004011684"}, {"class": "dessert", "prob": "0.0035615386"}, {"class": "vegetable_fruit", "prob": "0.0031584098"}, {"class": "bread", "prob": "0.002255855"}, {"class": "noodles_pasta", "prob": "0.00096961367"}, {"class": "dairy_products", "prob": "0.00040948062"}, {"class": "egg", "prob": "0.00021529438"}, {"class": "rice", "prob": "0.00017911145"}]}